scripts/__init__.py
scripts/clean_text.py
scripts/ent_ait_fix.py
scripts/fix_lines.py
scripts/liaisons.py
scripts/name_correction.py
scripts/pdf_2_txt.py
scripts/remove_pnum_hilight_title.py
scripts/replace_numbers.py
scripts/replace_special_chars.py
scripts/replace_words.py
scripts/split_chapters.py
atlas_solid_cleaning_text-0.1.0.dist-info/METADATA
atlas_solid_cleaning_text-0.1.0.dist-info/WHEEL
atlas_solid_cleaning_text-0.1.0.dist-info/top_level.txt
atlas_solid_cleaning_text-0.1.0.dist-info/RECORD
