Metadata-Version: 2.1
Name: atlas_solid_cleaning_text
Version: 0.1.0
Summary: Processes PDF files through various scripts to extract, clean, format and export text from a PDF file
Home-page: https://github.com/Atlas-dev-project/clean_text
Author: Str8-Up
Author-email: software@kampusmedia.ca
Classifier: Programming Language :: Python :: 3
Classifier: License :: OSI Approved :: MIT License
Classifier: Operating System :: OS Independent
Requires-Dist: spacy
Requires-Dist: elevenlabs
Requires-Dist: pdfplumber
Requires-Dist: openai
Requires-Dist: regex
Requires-Dist: num2words
